Pipelined 16bit ALU.srcs/sources_1/new/alu.sv
module alu(
input logic clk,
input logic areset,
input logic [2:0] opcode,
input logic [15:0] A,
input logic [15:0] B,
input logic [3:0] Dest_Reg,
input logic [3:0] Src_Reg_A,
input logic [3:0] Src_Reg_B,
output logic [15:0] outfinal,
output logic neg,
output logic zero,
output logic stall
    );

logic[2:0] op1;
logic[15:0] A1, B1;
logic[3:0] dest1;

always_ff@(posedge clk or posedge areset) begin
    if(areset) begin
        dest1 <= 0;
        op1 <= 0;
        A1 <= 0;
        B1 <= 0;
    end else if(stall)begin
        op1 <= 0;
        A1 <= 0;
        B1 <= 0;
        dest1 <= 0;
    end else begin
        dest1 <= Dest_Reg;
        op1 <= opcode;
        A1 <= A;
        B1 <= B; 
    end
end

logic[15:0] out1;
   
always_comb begin
    case(op1)
        3'b000: out1 = A1 + B1;
        3'b001: out1 = A1 - B1;
        3'b010: out1 = A1 & B1;
        3'b011: out1 = A1 | B1;
        3'b100: out1 = A1 ^ B1;
        3'b101: out1 = A1 << B1[3:0];
        3'b110: out1 = A1 >> B1[3:0];
        3'b111: out1 = A1 == B1;
        default: out1 = 0;
    endcase
end

logic[15:0] out2;
logic[3:0] dest2;
always_ff@(posedge clk or posedge areset) begin
    if(areset) begin
        dest2 <= 0;
        out2 <= 0;
    end else if(stall) begin
        dest2 <= 0;
        out2 <= 0;
    end else begin
        dest2 <= dest1; 
        out2 <= out1;
    end
end

always_ff@(posedge clk or posedge areset) begin
    if(areset) begin
        outfinal <= 0;
    end else begin
        outfinal <= out2;
    end
end

always_comb begin
    neg = (outfinal[15] == 1);
    zero = (outfinal == 0);
end

always_comb begin
    if ( ((dest1 == Src_Reg_A) || (dest1 == Src_Reg_B)) && (dest1 != 0) ) begin
        stall = 1;
    end else if ( ((dest2 == Src_Reg_A) || (dest2 == Src_Reg_B)) && (dest2 != 0) ) begin
        stall = 1;
    end else begin
        stall = 0;
    end
end
endmodule

Pipelined 16bit ALU.srcs/sim_1/new/testcases_tb.sv
import "DPI-C" function void alu_model(input byte unsigned opcode, input shortint unsigned A, input shortint unsigned B, output shortint unsigned pout, output byte unsigned pneg, output byte unsigned pzero);

module testcases_tb();

logic clk, areset;
logic [2:0] opcode;
logic [15:0] A, B;
logic [3:0] Dest_Reg, Src_Reg_A, Src_Reg_B;
logic [15:0] outfinal;
logic neg, zero, stall;

integer file_handle;

alu test(.*);

always #5 clk = ~clk;

logic [2:0] s_op1, s_op2;
logic [15:0] s_A1, s_A2, s_B1, s_B2;
logic [3:0] s_dest1, s_dest2;

initial begin
    shortint unsigned expected_ans;
    byte unsigned expected_neg, expected_zero;
    int i = 0, errors = 0;
    
    file_handle = $fopen("sim_data.csv", "w");
    $fdisplay(file_handle, "time,stall,opcode,outfinal");
    
    $dumpfile("alu_waves.vcd"); $dumpvars(0, testcases_tb);
    clk = 0; areset = 1; #15; areset = 0;

    while(i < 100) begin
        @(posedge clk); #1;
        
        $fdisplay(file_handle, "%0t,%d,%d,%d", $time, stall, opcode, outfinal);
        
        if(stall) begin
            s_op1 <= 0; s_A1 <= 0; s_B1 <= 0; s_dest1 <= 0;
            s_op2 <= 0; s_A2 <= 0; s_B2 <= 0; s_dest2 <= 0;
        end else begin
            s_op2 <= s_op1; s_A2 <= s_A1; s_B2 <= s_B1; s_dest2 <= s_dest1;
            
            A = $urandom(); B = $urandom(); opcode = $urandom_range(0,7);
            Dest_Reg = $urandom_range(1, 15);
            Src_Reg_A = $urandom_range(1, 15); Src_Reg_B = $urandom_range(1, 15);
            
            s_op1 <= opcode; s_A1 <= A; s_B1 <= B; s_dest1 <= Dest_Reg;
        end

        if(stall == 0 && i >= 2) begin 
            alu_model({5'b00000, s_op2}, s_A2, s_B2, expected_ans, expected_neg, expected_zero);
            
            if((outfinal !== expected_ans) || (neg !== expected_neg) || (zero !== expected_zero)) begin
                $display("Test %0d Failed | Opcode: %0d | Expected: %0d | Actual: %0d", i, s_op2, expected_ans, outfinal);
                errors++;
            end
            i++;
        end
    end
    
    $display("Simulation finished with %0d errors.", errors);
    $fclose(file_handle);
    $finish;
end
endmodule

Pipelined 16bit ALU.sim/sim_1/behav/xsim/alu_waves.vcd
$date
   Fri Jul  3 14:47:16 2026
$end

$version
  2025.2
  $dumpfile ("alu_waves.vcd") 
$end

$timescale
  1ps
$end

$scope module testcases_tb $end
$var reg 1 ! clk $end
$var reg 1 " areset $end
$var reg 3 # opcode [2:0] $end
$var reg 16 $ A [15:0] $end
$var reg 16 % B [15:0] $end
$var reg 4 & Dest_Reg [3:0] $end
$var reg 4 ' Src_Reg_A [3:0] $end
$var reg 4 ( Src_Reg_B [3:0] $end
$var reg 16 ) outfinal [15:0] $end
$var reg 1 * neg $end
$var reg 1 + zero $end
$var reg 1 , stall $end
$var integer 32 - file_handle [31:0] $end
$var reg 3 . s_op1 [2:0] $end
$var reg 3 / s_op2 [2:0] $end
$var reg 16 0 s_A1 [15:0] $end
$var reg 16 1 s_A2 [15:0] $end
$var reg 16 2 s_B1 [15:0] $end
$var reg 16 3 s_B2 [15:0] $end
$var reg 4 4 s_dest1 [3:0] $end
$var reg 4 5 s_dest2 [3:0] $end
$scope module test $end
$var wire 1 6 clk $end
$var wire 1 7 areset $end
$var wire 3 8 opcode [2:0] $end
$var wire 16 9 A [15:0] $end
$var wire 16 : B [15:0] $end
$var wire 4 ; Dest_Reg [3:0] $end
$var wire 4 < Src_Reg_A [3:0] $end
$var wire 4 = Src_Reg_B [3:0] $end
$var reg 16 ) outfinal [15:0] $end
$var reg 1 * neg $end
$var reg 1 + zero $end
$var reg 1 , stall $end
$var reg 3 > op1 [2:0] $end
$var reg 16 ? A1 [15:0] $end
$var reg 16 @ B1 [15:0] $end
$var reg 4 A dest1 [3:0] $end
$var reg 16 B out1 [15:0] $end
$var reg 16 C out2 [15:0] $end
$var reg 4 D dest2 [3:0] $end
$upscope $end
$scope begin Block22_8 $end
$var reg 16 E expected_ans [15:0] $end
$var reg 8 F expected_neg [7:0] $end
$var reg 8 G expected_zero [7:0] $end
$var reg 32 H i [31:0] $end
$var reg 32 I errors [31:0] $end
$upscope $end
$upscope $end
$enddefinitions $end

#0
$dumpvars
0!
1"
bx #
bx $
bx %
bx &
bx '
bx (
b0 )
0*
1+
0,
b11111111111111111011000111100000 -
bx .
bx /
bx 0
bx 1
bx 2
bx 3
bx 4
bx 5
06
17
bx 8
bx 9
bx :
bx ;
bx <
bx =
b0 >
b0 ?
b0 @
b0 A
b0 B
b0 C
b0 D
b0 E
b0 F
b0 G
b0 H
b0 I
$end

#5000
1!
16

#10000
0!
06

#15000
1!
0"
16
07
bx >
bx ?
bx @
bx A

#16000
b100 #
b1111100111100011 $
b100100001011 %
b1000 &
b1 '
b100 (
b100 .
b1111100111100011 0
b100100001011 2
b1000 4
b100 8
b1111100111100011 9
b100100001011 :
b1000 ;
b1 <
b100 =

#20000
0!
06

#25000
1!
16
b100 >
b1111100111100011 ?
b100100001011 @
b1000 A
b1111000011101000 B
bx D

#26000
b101 #
b1111100001000011 $
b10101110101000 %
b1011 &
b1001 '
b1011 (
b101 .
b100 /
b1111100001000011 0
b1111100111100011 1
b10101110101000 2
b100100001011 3
b1011 4
b1000 5
b101 8
b1111100001000011 9
b10101110101000 :
b1011 ;
b1001 <
b1011 =

#30000
0!
06

#35000
1!
1,
16
b101 >
b1111100001000011 ?
b10101110101000 @
b1011 A
b100001100000000 B
b1111000011101000 C
b1000 D

#36000
b0 .
b0 /
b0 0
b0 1
b0 2
b0 3
b0 4
b0 5

#40000
0!
06

#45000
1!
b1111000011101000 )
1*
0+
0,
16
b0 >
b0 ?
b0 @
b0 A
b0 B
b0 C
b0 D

#46000
b10 #
b111011011011000 $
b101001111100010 %
b1001 &
b1000 '
b101 (
b10 .
b111011011011000 0
b101001111100010 2
b1001 4
b10 8
b111011011011000 9
b101001111100010 :
b1001 ;
b1000 <
b101 =

#50000
0!
06

#55000
1!
b0 )
0*
1+
16
b10 >
b111011011011000 ?
b101001111100010 @
b1001 A
b101001011000000 B

#56000
b11 #
b1000000000110111 $
b1101111011010001 %
b1000 &
b1110 '
b1001 (
1,
b11 .
b10 /
b1000000000110111 0
b111011011011000 1
b1101111011010001 2
b101001111100010 3
b1000 4
b1001 5
b11 8
b1000000000110111 9
b1101111011010001 :
b1000 ;
b1110 <
b1001 =

#60000
0!
06

#65000
1!
0,
16
b0 >
b0 ?
b0 @
b0 A
b0 B

#66000
b110 #
b110111001001011 $
b100000110101110 %
b1101 &
b1111 '
b11 (
b110 .
b11 /
b110111001001011 0
b1000000000110111 1
b100000110101110 2
b1101111011010001 3
b1101 4
b1000 5
b110 8
b110111001001011 9
b100000110101110 :
b1101 ;
b1111 <
b11 =

#70000
0!
06

#75000
1!
16
b110 >
b110111001001011 ?
b100000110101110 @
b1101 A
b1 B

#76000
b11 #
b1100011110111011 $
b1111100101101100 %
b1010 &
b110 '
b10 (
b11 .
b110 /
b1100011110111011 0
b110111001001011 1
b1111100101101100 2
b100000110101110 3
b1010 4
b1101 5
b11 8
b1100011110111011 9
b1111100101101100 :
b1010 ;
b110 <
b10 =

#80000
0!
06

#85000
1!
16
b11 >
b1100011110111011 ?
b1111100101101100 @
b1010 A
b1111111111111111 B
b1 C
b1101 D

#86000
b0 #
b100000111110 $
b1010100000101110 %
b1110 &
b100 '
b1000 (
b0 .
b11 /
b100000111110 0
b1100011110111011 1
b1010100000101110 2
b1111100101101100 3
b1110 4
b1010 5
b0 8
b100000111110 9
b1010100000101110 :
b1110 ;
b100 <
b1000 =

#90000
0!
06

#95000
1!
b1 )
0+
16
b0 >
b100000111110 ?
b1010100000101110 @
b1110 A
b1011000001101100 B
b1111111111111111 C
b1010 D

#96000
b1 #
b1100010110110 $
b11011110101110 %
b1000 &
b11 '
b11 (
b1 .
b0 /
b1100010110110 0
b100000111110 1
b11011110101110 2
b1010100000101110 3
b1000 4
b1110 5
b1 8
b1100010110110 9
b11011110101110 :
b1000 ;
b11 <
b11 =

#100000
0!
06

#105000
1!
b1111111111111111 )
1*
16
b1 >
b1100010110110 ?
b11011110101110 @
b1000 A
b1110000100001000 B
b1011000001101100 C
b1110 D

#106000
b0 #
b1000011110011001 $
b1101101001110 %
b110 &
b1110 '
b1010 (
1,
b0 .
b1 /
b1000011110011001 0
b1100010110110 1
b1101101001110 2
b11011110101110 3
b110 4
b1000 5
b0 8
b1000011110011001 9
b1101101001110 :
b110 ;
b1110 <
b1010 =

#110000
0!
06

#115000
1!
b1011000001101100 )
0,
16
b0 >
b0 ?
b0 @
b0 A
b0 B
b0 C
b0 D

#116000
b111 #
b101011010111100 $
b1011010101 %
b111 &
b1001 '
b111 (
b111 .
b0 /
b101011010111100 0
b1000011110011001 1
b1011010101 2
b1101101001110 3
b111 4
b110 5
b111 8
b101011010111100 9
b1011010101 :
b111 ;
b1001 <
b111 =

#120000
0!
06

#125000
1!
b0 )
0*
1+
1,
16
b111 >
b101011010111100 ?
b1011010101 @
b111 A

#126000
b0 .
b0 0
b0 1
b0 2
b0 3
b0 4
b0 5

#130000
0!
06

#135000
1!
0,
16
b0 >
b0 ?
b0 @
b0 A

#136000
b1 #
b1100011101000100 $
b1011000100000100 %
b1001 &
b1101 '
b1010 (
b1 .
b1100011101000100 0
b1011000100000100 2
b1001 4
b1 8
b1100011101000100 9
b1011000100000100 :
b1001 ;
b1101 <
b1010 =

#140000
0!
06

#145000
1!
16
b1 >
b1100011101000100 ?
b1011000100000100 @
b1001 A
b1011001000000 B

#146000
b101 #
b1110110000111111 $
b10111111100 %
b1000 &
b110 '
b1100 (
b101 .
b1 /
b1110110000111111 0
b1100011101000100 1
b10111111100 2
b1011000100000100 3
b1000 4
b1001 5
b101 8
b1110110000111111 9
b10111111100 :
b1000 ;
b110 <
b1100 =

#150000
0!
06

#155000
1!
16
b101 >
b1110110000111111 ?
b10111111100 @
b1000 A
b1111000000000000 B
b1011001000000 C
b1001 D

#156000
b1 #
b1110110001101001 $
b111001011111 %
b1 &
b100 '
b101 (
b1 .
b101 /
b1110110001101001 0
b1110110000111111 1
b111001011111 2
b10111111100 3
b1 4
b1000 5
b1 8
b1110110001101001 9
b111001011111 :
b1 ;
b100 <
b101 =

#160000
0!
06

#165000
1!
b1011001000000 )
0+
16
b1 >
b1110110001101001 ?
b111001011111 @
b1 A
b1101111000001010 B
b1111000000000000 C
b1000 D

#166000
b0 #
b1110011110011011 $
b1011100111111000 %
b1011 &
b11 '
b1010 (
b0 .
b1 /
b1110011110011011 0
b1110110001101001 1
b1011100111111000 2
b111001011111 3
b1011 4
b1 5
b0 8
b1110011110011011 9
b1011100111111000 :
b1011 ;
b11 <
b1010 =

#170000
0!
06

#175000
1!
b1111000000000000 )
1*
16
b0 >
b1110011110011011 ?
b1011100111111000 @
b1011 A
b1010000110010011 B
b1101111000001010 C
b1 D

#176000
b111 #
b100111110011110 $
b110110000111001 %
b1110 &
b111 '
b110 (
b111 .
b0 /
b100111110011110 0
b1110011110011011 1
b110110000111001 2
b1011100111111000 3
b1110 4
b1011 5
b111 8
b100111110011110 9
b110110000111001 :
b1110 ;
b111 <
b110 =

#180000
0!
06

#185000
1!
b1101111000001010 )
16
b111 >
b100111110011110 ?
b110110000111001 @
b1110 A
b0 B
b1010000110010011 C
b1011 D

#186000
b110 #
b1100010000001110 $
b1100011001100011 %
b100 &
b1011 '
b1111 (
1,
b110 .
b111 /
b1100010000001110 0
b100111110011110 1
b1100011001100011 2
b110110000111001 3
b100 4
b1110 5
b110 8
b1100010000001110 9
b1100011001100011 :
b100 ;
b1011 <
b1111 =

#190000
0!
06

#195000
1!
b1010000110010011 )
0,
16
b0 >
b0 ?
b0 @
b0 A
b0 C
b0 D

#196000
b111 #
b1111111010011011 $
b10110110000000 %
b1001 &
b1101 '
b111 (
b111 .
b110 /
b1111111010011011 0
b1100010000001110 1
b10110110000000 2
b1100011001100011 3
b1001 4
b100 5
b111 8
b1111111010011011 9
b10110110000000 :
b1001 ;
b1101 <
b111 =

#200000
0!
06

#205000
1!
b0 )
0*
1+
16
b111 >
b1111111010011011 ?
b10110110000000 @
b1001 A

#206000
b1 #
b110011111101 $
b1100101100100000 %
b1100 &
b110 '
b101 (
b1 .
b111 /
b110011111101 0
b1111111010011011 1
b1100101100100000 2
b10110110000000 3
b1100 4
b1001 5
b1 8
b110011111101 9
b1100101100100000 :
b1100 ;
b110 <
b101 =

#210000
0!
06

#215000
1!
16
b1 >
b110011111101 ?
b1100101100100000 @
b1100 A
b100000111011101 B
b1001 D

#216000
b111 #
b1000100001011110 $
b1010001010000111 %
b1001 &
b111 '
b1101 (
b111 .
b1 /
b1000100001011110 0
b110011111101 1
b1010001010000111 2
b1100101100100000 3
b1001 4
b1100 5
b111 8
b1000100001011110 9
b1010001010000111 :
b1001 ;
b111 <
b1101 =

#220000
0!
06

#225000
1!
16
b111 >
b1000100001011110 ?
b1010001010000111 @
b1001 A
b0 B
b100000111011101 C
b1100 D

#226000
b1 #
b1001010010110111 $
b100000011011011 %
b1101 &
b1 '
b1111 (
b1 .
b111 /
b1001010010110111 0
b1000100001011110 1
b100000011011011 2
b1010001010000111 3
b1101 4
b1001 5
b1 8
b1001010010110111 9
b100000011011011 :
b1101 ;
b1 <
b1111 =

#230000
0!
06

#235000
1!
b100000111011101 )
0+
16
b1 >
b1001010010110111 ?
b100000011011011 @
b1101 A
b101001111011100 B
b0 C
b1001 D

#236000
b0 #
b1001100101100000 $
b1111110111011010 %
b11 &
b10 '
b1110 (
b0 .
b1 /
b1001100101100000 0
b1001010010110111 1
b1111110111011010 2
b100000011011011 3
b11 4
b1101 5
b0 8
b1001100101100000 9
b1111110111011010 :
b11 ;
b10 <
b1110 =

#240000
0!
06

#245000
1!
b0 )
1+
16
b0 >
b1001100101100000 ?
b1111110111011010 @
b11 A
b1001011100111010 B
b101001111011100 C
b1101 D

#246000
b101 #
b11000100011110 $
b110001110000000 %
b110 &
b1100 '
b1100 (
b101 .
b0 /
b11000100011110 0
b1001100101100000 1
b110001110000000 2
b1111110111011010 3
b110 4
b11 5
b101 8
b11000100011110 9
b110001110000000 :
b110 ;
b1100 <
b1100 =

#250000
0!
06

#255000
1!
b101001111011100 )
0+
16
b101 >
b11000100011110 ?
b110001110000000 @
b110 A
b11000100011110 B
b1001011100111010 C
b11 D

#256000
b110 #
b110110000110010 $
b1001110110100000 %
b10 '
b10 (
b110 .
b101 /
b110110000110010 0
b11000100011110 1
b1001110110100000 2
b110001110000000 3
b110 5
b110 8
b110110000110010 9
b1001110110100000 :
b10 <
b10 =

#260000
0!
06

#265000
1!
b1001011100111010 )
1*
16
b110 >
b110110000110010 ?
b1001110110100000 @
b110110000110010 B
b11000100011110 C
b110 D

#266000
b0 #
b1101011000111110 $
b1010001111101001 %
b101 &
b1000 '
b100 (
b0 .
b110 /
b1101011000111110 0
b110110000110010 1
b1010001111101001 2
b1001110110100000 3
b101 4
b0 8
b1101011000111110 9
b1010001111101001 :
b101 ;
b1000 <
b100 =

#270000
0!
06

#275000
1!
b11000100011110 )
0*
16
b0 >
b1101011000111110 ?
b1010001111101001 @
b101 A
b111101000100111 B
b110110000110010 C

#276000
b11110111101100 $
b1011011001001111 %
b1111 &
b100 '
b1110 (
b0 /
b11110111101100 0
b1101011000111110 1
b1011011001001111 2
b1010001111101001 3
b1111 4
b101 5
b11110111101100 9
b1011011001001111 :
b1111 ;
b100 <
b1110 =

#280000
0!
06

#285000
1!
b110110000110010 )
16
b11110111101100 ?
b1011011001001111 @
b1111 A
b1111010000111011 B
b111101000100111 C
b101 D

#286000
b1 #
b1000010100010011 $
b1100100000010000 %
b1001 &
b1110 '
b1 .
b1000010100010011 0
b11110111101100 1
b1100100000010000 2
b1011011001001111 3
b1001 4
b1111 5
b1 8
b1000010100010011 9
b1100100000010000 :
b1001 ;
b1110 <

#290000
0!
06

#295000
1!
b111101000100111 )
16
b1 >
b1000010100010011 ?
b1100100000010000 @
b1001 A
b1011110100000011 B
b1111010000111011 C
b1111 D

#296000
b110 #
b10101111010110 $
b1001001011001000 %
b1 &
b111 '
b1010 (
b110 .
b1 /
b10101111010110 0
b1000010100010011 1
b1001001011001000 2
b1100100000010000 3
b1 4
b1001 5
b110 8
b10101111010110 9
b1001001011001000 :
b1 ;
b111 <
b1010 =

#300000
0!
06

#305000
1!
b1111010000111011 )
1*
16
b110 >
b10101111010110 ?
b1001001011001000 @
b1 A
b101011 B
b1011110100000011 C
b1001 D

#306000
b11 #
b1010100101101101 $
b10011100001010 %
b1010 &
b1100 '
b1110 (
b11 .
b110 /
b1010100101101101 0
b10101111010110 1
b10011100001010 2
b1001001011001000 3
b1010 4
b1 5
b11 8
b1010100101101101 9
b10011100001010 :
b1010 ;
b1100 <
b1110 =

#310000
0!
06

#315000
1!
b1011110100000011 )
16
b11 >
b1010100101101101 ?
b10011100001010 @
b1010 A
b1010111101101111 B
b101011 C
b1 D

#316000
b10 #
b100111011111110 $
b111011000000111 %
b11 &
b11 '
b1100 (
b10 .
b11 /
b100111011111110 0
b1010100101101101 1
b111011000000111 2
b10011100001010 3
b11 4
b1010 5
b10 8
b100111011111110 9
b111011000000111 :
b11 ;
b11 <
b1100 =

#320000
0!
06

#325000
1!
b101011 )
0*
1,
16
b10 >
b100111011111110 ?
b111011000000111 @
b11 A
b100011000000110 B
b1010111101101111 C
b1010 D

#326000
b0 .
b0 /
b0 0
b0 1
b0 2
b0 3
b0 4
b0 5

#330000
0!
06

#335000
1!
b1010111101101111 )
1*
0,
16
b0 >
b0 ?
b0 @
b0 A
b0 B
b0 C
b0 D

#336000
b11 #
b10001100001001 $
b11101001100000 %
b1 &
b1110 '
b1110 (
b11 .
b10001100001001 0
b11101001100000 2
b1 4
b11 8
b10001100001001 9
b11101001100000 :
b1 ;
b1110 <
b1110 =

#340000
0!
06

#345000
1!
b0 )
0*
1+
16
b11 >
b10001100001001 ?
b11101001100000 @
b1 A
b11101101101001 B

#346000
b101 #
b110011111000 $
b1100011010011 %
b1111 &
b1 (
1,
b101 .
b11 /
b110011111000 0
b10001100001001 1
b1100011010011 2
b11101001100000 3
b1111 4
b1 5
b101 8
b110011111000 9
b1100011010011 :
b1111 ;
b1 =

#350000
0!
06

#355000
1!
0,
16
b0 >
b0 ?
b0 @
b0 A
b0 B

#356000
b10 #
b1001101011110001 $
b1101011101111111 %
b1000 &
b1000 '
b11 (
b10 .
b101 /
b1001101011110001 0
b110011111000 1
b1101011101111111 2
b1100011010011 3
b1000 4
b1111 5
b10 8
b1001101011110001 9
b1101011101111111 :
b1000 ;
b1000 <
b11 =

#360000
0!
06

#365000
1!
1,
16
b10 >
b1001101011110001 ?
b1101011101111111 @
b1000 A
b1001001001110001 B

#366000
b0 .
b0 /
b0 0
b0 1
b0 2
b0 3
b0 4
b0 5

#370000
0!
06

#375000
1!
0,
16
b0 >
b0 ?
b0 @
b0 A
b0 B

#376000
b0 #
b111111011010110 $
b101000010110101 %
b101 &
b100 '
b111111011010110 0
b101000010110101 2
b101 4
b0 8
b111111011010110 9
b101000010110101 :
b101 ;
b100 <

#380000
0!
06

#385000
1!
16
b111111011010110 ?
b101000010110101 @
b101 A
b1100111110001011 B

#386000
b1 #
b101010010110001 $
b110000110001010 %
b1000 &
b101 '
b1 (
1,
b1 .
b101010010110001 0
b111111011010110 1
b110000110001010 2
b101000010110101 3
b1000 4
b101 5
b1 8
b101010010110001 9
b110000110001010 :
b1000 ;
b101 <
b1 =

#390000
0!
06

#395000
1!
0,
16
b0 ?
b0 @
b0 A
b0 B

#396000
b111 #
b101100111010101 $
b11101010111011 %
b110 &
b10 '
b1100 (
b111 .
b1 /
b101100111010101 0
b101010010110001 1
b11101010111011 2
b110000110001010 3
b110 4
b1000 5
b111 8
b101100111010101 9
b11101010111011 :
b110 ;
b10 <
b1100 =

#400000
0!
06

#405000
1!
16
b111 >
b101100111010101 ?
b11101010111011 @
b110 A

#406000
b100 #
b1001100011011011 $
b1001000011110010 %
b101 &
b1111 '
b1110 (
b100 .
b111 /
b1001100011011011 0
b101100111010101 1
b1001000011110010 2
b11101010111011 3
b101 4
b110 5
b100 8
b1001100011011011 9
b1001000011110010 :
b101 ;
b1111 <
b1110 =

#410000
0!
06

#415000
1!
16
b100 >
b1001100011011011 ?
b1001000011110010 @
b101 A
b100000101001 B
b110 D

#416000
b10 #
b110001110110011 $
b11000111001100 %
b1101 &
b111 (
b10 .
b100 /
b110001110110011 0
b1001100011011011 1
b11000111001100 2
b1001000011110010 3
b1101 4
b101 5
b10 8
b110001110110011 9
b11000111001100 :
b1101 ;
b111 =

#420000
0!
06

#425000
1!
16
b10 >
b110001110110011 ?
b11000111001100 @
b1101 A
b10000110000000 B
b100000101001 C
b101 D

#426000
b111 #
b1100000100101000 $
b10000011000010 %
b1010 &
b100 '
b1000 (
b111 .
b10 /
b1100000100101000 0
b110001110110011 1
b10000011000010 2
b11000111001100 3
b1010 4
b1101 5
b111 8
b1100000100101000 9
b10000011000010 :
b1010 ;
b100 <
b1000 =

#430000
0!
06

#435000
1!
b100000101001 )
0+
16
b111 >
b1100000100101000 ?
b10000011000010 @
b1010 A
b0 B
b10000110000000 C
b1101 D

#436000
b1000010001101 $
b101100011001001 %
b1000 &
b1111 '
b1001 (
b111 /
b1000010001101 0
b1100000100101000 1
b101100011001001 2
b10000011000010 3
b1000 4
b1010 5
b1000010001101 9
b101100011001001 :
b1000 ;
b1111 <
b1001 =

#440000
0!
06

#445000
1!
b10000110000000 )
16
b1000010001101 ?
b101100011001001 @
b1000 A
b0 C
b1010 D

#446000
b10 #
b1100110001010 $
b10110111001 %
b1100 &
b1101 '
b1101 (
b10 .
b1100110001010 0
b1000010001101 1
b10110111001 2
b101100011001001 3
b1100 4
b1000 5
b10 8
b1100110001010 9
b10110111001 :
b1100 ;
b1101 <
b1101 =

#450000
0!
06

#455000
1!
b0 )
1+
16
b10 >
b1100110001010 ?
b10110111001 @
b1100 A
b110001000 B
b1000 D

#456000
b0 #
b1011100010111010 $
b1101010111001000 %
b11 &
b1111 '
b1 (
b0 .
b10 /
b1011100010111010 0
b1100110001010 1
b1101010111001000 2
b10110111001 3
b11 4
b1100 5
b0 8
b1011100010111010 9
b1101010111001000 :
b11 ;
b1111 <
b1 =

#460000
0!
06

#465000
1!
16
b0 >
b1011100010111010 ?
b1101010111001000 @
b11 A
b1000111010000010 B
b110001000 C
b1100 D

#466000
b110 #
b1001011001001011 $
b10101111010100 %
b10 &
b1110 '
b1001 (
b110 .
b0 /
b1001011001001011 0
b1011100010111010 1
b10101111010100 2
b1101010111001000 3
b10 4
b11 5
b110 8
b1001011001001011 9
b10101111010100 :
b10 ;
b1110 <
b1001 =

#470000
0!
06

#475000
1!
b110001000 )
0+
16
b110 >
b1001011001001011 ?
b10101111010100 @
b10 A
b100101100100 B
b1000111010000010 C
b11 D

#476000
b11 #
b11000010111001 $
b1110111100001100 %
b11 &
b1101 '
b11 .
b110 /
b11000010111001 0
b1001011001001011 1
b1110111100001100 2
b10101111010100 3
b11 4
b10 5
b11 8
b11000010111001 9
b1110111100001100 :
b11 ;
b1101 <

#480000
0!
06

#485000
1!
b1000111010000010 )
1*
16
b11 >
b11000010111001 ?
b1110111100001100 @
b11 A
b1111111110111101 B
b100101100100 C
b10 D

#486000
b1 #
b1010011000001111 $
b10010100101001 %
b1110 &
b1111 '
b1010 (
b1 .
b11 /
b1010011000001111 0
b11000010111001 1
b10010100101001 2
b1110111100001100 3
b1110 4
b11 5
b1 8
b1010011000001111 9
b10010100101001 :
b1110 ;
b1111 <
b1010 =

#490000
0!
06

#495000
1!
b100101100100 )
0*
16
b1 >
b1010011000001111 ?
b10010100101001 @
b1110 A
b1000000011100110 B
b1111111110111101 C
b11 D

#496000
b10 #
b11111011100111 $
b1111110100010000 %
b11 &
b1000 '
b1101 (
b10 .
b1 /
b11111011100111 0
b1010011000001111 1
b1111110100010000 2
b10010100101001 3
b11 4
b1110 5
b10 8
b11111011100111 9
b1111110100010000 :
b11 ;
b1000 <
b1101 =

#500000
0!
06

#505000
1!
b1111111110111101 )
1*
16
b10 >
b11111011100111 ?
b1111110100010000 @
b11 A
b11110000000000 B
b1000000011100110 C
b1110 D

#506000
b11 #
b1100001001 $
b1000001000010001 %
b1001 &
b1111 '
b11 .
b10 /
b1100001001 0
b11111011100111 1
b1000001000010001 2
b1111110100010000 3
b1001 4
b11 5
b11 8
b1100001001 9
b1000001000010001 :
b1001 ;
b1111 <

#510000
0!
06

#515000
1!
b1000000011100110 )
16
b11 >
b1100001001 ?
b1000001000010001 @
b1001 A
b1000001100011001 B
b11110000000000 C
b11 D

#516000
b111 #
b101110011101111 $
b1010101111011010 %
b1011 &
b11 '
b1010 (
1,
b111 .
b11 /
b101110011101111 0
b1100001001 1
b1010101111011010 2
b1000001000010001 3
b1011 4
b1001 5
b111 8
b101110011101111 9
b1010101111011010 :
b1011 ;
b11 <
b1010 =

#520000
0!
06

#525000
1!
b11110000000000 )
0*
0,
16
b0 >
b0 ?
b0 @
b0 A
b0 B
b0 C
b0 D

#526000
b11 #
b100101100100000 $
b110101000101 %
b1001 &
b10 '
b101 (
b11 .
b111 /
b100101100100000 0
b101110011101111 1
b110101000101 2
b1010101111011010 3
b1001 4
b1011 5
b11 8
b100101100100000 9
b110101000101 :
b1001 ;
b10 <
b101 =

#530000
0!
06

#535000
1!
b0 )
1+
16
b11 >
b100101100100000 ?
b110101000101 @
b1001 A
b100111101100101 B

#536000
b110 #
b10100101110001 $
b101011011000 %
b1100 &
b110 .
b11 /
b10100101110001 0
b100101100100000 1
b101011011000 2
b110101000101 3
b1100 4
b1001 5
b110 8
b10100101110001 9
b101011011000 :
b1100 ;

#540000
0!
06

#545000
1!
16
b110 >
b10100101110001 ?
b101011011000 @
b1100 A
b101001 B
b100111101100101 C
b1001 D

#546000
b1011100010011110 $
b1001101000101001 %
b11 &
b1101 '
b110 /
b1011100010011110 0
b10100101110001 1
b1001101000101001 2
b101011011000 3
b11 4
b1100 5
b1011100010011110 9
b1001101000101001 :
b11 ;
b1101 <

#550000
0!
06

#555000
1!
b100111101100101 )
0+
16
b1011100010011110 ?
b1001101000101001 @
b11 A
b1011100 B
b101001 C
b1100 D

#556000
b111 #
b1101001001100010 $
b1110101110100011 %
b1001 &
b1110 '
b10 (
b111 .
b1101001001100010 0
b1011100010011110 1
b1110101110100011 2
b1001101000101001 3
b1001 4
b11 5
b111 8
b1101001001100010 9
b1110101110100011 :
b1001 ;
b1110 <
b10 =

#560000
0!
06

#565000
1!
b101001 )
16
b111 >
b1101001001100010 ?
b1110101110100011 @
b1001 A
b0 B
b1011100 C
b11 D

#566000
b0 #
b11001001000110 $
b1010001110101010 %
b1 &
b100 '
b1011 (
b0 .
b111 /
b11001001000110 0
b1101001001100010 1
b1010001110101010 2
b1110101110100011 3
b1 4
b1001 5
b0 8
b11001001000110 9
b1010001110101010 :
b1 ;
b100 <
b1011 =

#570000
0!
06

#575000
1!
b1011100 )
16
b0 >
b11001001000110 ?
b1010001110101010 @
b1 A
b1101010111110000 B
b0 C
b1001 D

#576000
b10 #
b110101000111010 $
b1001111111101001 %
b1110 &
b111 '
b1001 (
1,
b10 .
b0 /
b110101000111010 0
b11001001000110 1
b1001111111101001 2
b1010001110101010 3
b1110 4
b1 5
b10 8
b110101000111010 9
b1001111111101001 :
b1110 ;
b111 <
b1001 =

#580000
0!
06

#585000
1!
b0 )
1+
0,
16
b0 ?
b0 @
b0 A
b0 B
b0 D

