Pipelined 16bit ALU.srcs/sources_1/new/alu.sv
module alu(
input logic clk,
input logic areset,
input logic [2:0] opcode,
input logic [15:0] A,
input logic [15:0] B,
input logic [3:0] Dest_Reg,
input logic [3:0] Src_Reg_A,
input logic [3:0] Src_Reg_B,
output logic [15:0] outfinal,
output logic neg,
output logic zero,
output logic stall
    );

logic[2:0] op1;
logic[15:0] A1, B1;
logic[3:0] dest1;

always_ff@(posedge clk or posedge areset) begin
    if(areset) begin
        dest1 <= 0;
        op1 <= 0;
        A1 <= 0;
        B1 <= 0;
    end else if(stall)begin
        op1 <= 0;
        A1 <= 0;
        B1 <= 0;
        dest1 <= 0;
    end else begin
        dest1 <= Dest_Reg;
        op1 <= opcode;
        A1 <= A;
        B1 <= B; 
    end
end

logic[15:0] out1;
   
always_comb begin
    case(op1)
        3'b000: out1 = A1 + B1;
        3'b001: out1 = A1 - B1;
        3'b010: out1 = A1 & B1;
        3'b011: out1 = A1 | B1;
        3'b100: out1 = A1 ^ B1;
        3'b101: out1 = A1 << B1[3:0];
        3'b110: out1 = A1 >> B1[3:0];
        3'b111: out1 = A1 == B1;
        default: out1 = 0;
    endcase
end

logic[15:0] out2;
logic[3:0] dest2;
always_ff@(posedge clk or posedge areset) begin
    if(areset) begin
        dest2 <= 0;
        out2 <= 0;
    end else begin
        dest2 <= dest1; 
        out2 <= out1;
    end
end

always_ff@(posedge clk or posedge areset) begin
    if(areset) begin
        outfinal <= 0;
    end else begin
        outfinal <= out2;
    end
end

always_comb begin
    neg = (outfinal[15] == 1);
    zero = (outfinal == 0);
end

always_comb begin
    if ( ((dest1 == Src_Reg_A) || (dest1 == Src_Reg_B)) && (dest1 != 0) ) begin
        stall = 1;
    end else if ( ((dest2 == Src_Reg_A) || (dest2 == Src_Reg_B)) && (dest2 != 0) ) begin
        stall = 1;
    end else begin
        stall = 0;
    end
end
endmodule

Pipelined 16bit ALU.srcs/sim_1/new/testcases_tb.sv
import "DPI-C" function void alu_model(input byte unsigned opcode, input shortint unsigned A, input shortint unsigned B, output shortint unsigned pout, output byte unsigned pneg, output byte unsigned pzero);

module testcases_tb(
    );
    
logic clk;
logic areset;
logic [2:0] opcode;
logic [15:0] A;
logic [15:0] B;
logic [3:0] Dest_Reg;
logic [3:0] Src_Reg_A;
logic [3:0] Src_Reg_B;
logic [15:0] outfinal;
logic neg;
logic zero;
logic stall;

shortint unsigned expected_ans;
byte unsigned expected_neg;
byte unsigned expected_zero;

alu test(
    .clk(clk),
    .areset(areset),
    .opcode(opcode),
    .A(A),
    .B(B),
    .Dest_Reg(Dest_Reg),
    .Src_Reg_A(Src_Reg_A),
    .Src_Reg_B(Src_Reg_B),
    .outfinal(outfinal),
    .neg(neg),
    .zero(zero),
    .stall(stall)
);

always #5 clk = ~clk;
int errors = 0;

covergroup cg @(posedge clk);
    track_opcode: coverpoint opcode{
        bins track_add = {3'b000};
        bins track_sub = {3'b001};
        bins track_and = {3'b010};
        bins track_or = {3'b011};
        bins track_xor = {3'b100};
        bins track_ls = {3'b101};
        bins track_rs = {3'b110};
        bins track_equal = {3'b111};
    }
endgroup

initial begin
    cg inst = new();
    $dumpfile("alu_waves.vcd");
    $dumpvars(0, testcases_tb);
    clk = 0;
    areset = 1;
    opcode = 0;
    A = 0;
    B = 0;
    Dest_Reg = 0;
    Src_Reg_A = 0;
    Src_Reg_B = 0;
    
    #15;
    
    areset = 0;
    $display("-----------Test Starting-----------");
    
    for(int i = 0; i < 100; i++) begin
        A = $urandom();
        B = $urandom();
        opcode = $urandom_range(0,7);
        Dest_Reg = 1;
        Src_Reg_A = 0;
        Src_Reg_B = 0;
         
        alu_model({5'b00000,opcode}, A, B, expected_ans, expected_neg, expected_zero);
        @(posedge clk);
        @(posedge clk);
        @(posedge clk);
        #1;
        
        if((outfinal != expected_ans) || (neg != expected_neg) || (zero != expected_zero)) begin
            $display("Test %0d Failed| Opcode: %0d   A: %0d   B: %0d", i, opcode, A, B);
            $display("Expected| Answer: %0d   Negative: %0d   Zero: %0d", expected_ans, expected_neg, expected_zero);
            $display("Actual| Answer: %0d   Negative: %0d   Zero: %0d", outfinal, neg, zero);
            errors++;
        end
    end
    
    $display("-----------Final Results-----------");
    if(errors == 0) begin
        $display("You have no errors!!");
    end else begin
        $display("You failed %0d testcases", errors);
    end
    
    $display("Functional Coverage: %0.2f%%", inst.get_inst_coverage());
    $display("-----------End-----------");
    $finish;
end

assert property (@(posedge clk) areset |=> (outfinal == 0));

assert property(@(posedge clk) (Src_Reg_A == test.dest1) && (Src_Reg_A != 0)|-> (stall == 1));
assert property(@(posedge clk) (Src_Reg_A == test.dest2) && (Src_Reg_A != 0)|-> (stall == 1));
assert property(@(posedge clk) (Src_Reg_B == test.dest1) && (Src_Reg_B != 0)|-> (stall == 1));
assert property(@(posedge clk) (Src_Reg_B == test.dest2) && (Src_Reg_B != 0)|-> (stall == 1));

assert property(@(posedge clk) (stall == 1) |=> (test.dest1 == 0) && (test.op1 == 0) && (test.A1 == 0) && (test.B1 == 0));

assert property(@(posedge clk) (outfinal[15] == 1) |-> (neg != 0));
assert property(@(posedge clk) (outfinal == 0) |-> (zero != 0));


endmodule

Pipelined 16bit ALU.sim/sim_1/behav/xsim/alu_waves.vcd
$date
   Thu Jul  2 15:02:07 2026
$end

$version
  2025.2
  $dumpfile ("alu_waves.vcd") 
$end

$timescale
  1ps
$end

$scope module testcases_tb $end
$var reg 1 ! clk $end
$var reg 1 " areset $end
$var reg 3 # opcode [2:0] $end
$var reg 16 $ A [15:0] $end
$var reg 16 % B [15:0] $end
$var reg 4 & Dest_Reg [3:0] $end
$var reg 4 ' Src_Reg_A [3:0] $end
$var reg 4 ( Src_Reg_B [3:0] $end
$var reg 16 ) outfinal [15:0] $end
$var reg 1 * neg $end
$var reg 1 + zero $end
$var reg 1 , stall $end
$var reg 16 - expected_ans [15:0] $end
$var reg 8 . expected_neg [7:0] $end
$var reg 8 / expected_zero [7:0] $end
$var reg 32 0 errors [31:0] $end
$scope module test $end
$var wire 1 1 clk $end
$var wire 1 2 areset $end
$var wire 3 3 opcode [2:0] $end
$var wire 16 4 A [15:0] $end
$var wire 16 5 B [15:0] $end
$var wire 4 6 Dest_Reg [3:0] $end
$var wire 4 7 Src_Reg_A [3:0] $end
$var wire 4 8 Src_Reg_B [3:0] $end
$var reg 16 ) outfinal [15:0] $end
$var reg 1 * neg $end
$var reg 1 + zero $end
$var reg 1 , stall $end
$var reg 3 9 op1 [2:0] $end
$var reg 16 : A1 [15:0] $end
$var reg 16 ; B1 [15:0] $end
$var reg 4 < dest1 [3:0] $end
$var reg 16 = out1 [15:0] $end
$var reg 16 > out2 [15:0] $end
$var reg 4 ? dest2 [3:0] $end
$upscope $end
$scope begin Block54_12 $end
$scope begin Block72_13 $end
$var reg 32 @ i [31:0] $end
$upscope $end
$upscope $end
$scope function xlnx_isim_covergroup_cg::new $end
$upscope $end
$scope function xlnx_isim_covergroup_cg::update $end
$upscope $end
$scope function xlnx_isim_covergroup_cg::xlnx_isim_covergroup_sample $end
$upscope $end
$upscope $end
$enddefinitions $end

#0
$dumpvars
0!
1"
b0 #
b0 $
b0 %
b0 &
b0 '
b0 (
b0 )
0*
1+
0,
b0 -
b0 .
b0 /
b0 0
01
12
b0 3
b0 4
b0 5
b0 6
b0 7
b0 8
b0 9
b0 :
b0 ;
b0 <
b0 =
b0 >
b0 ?
b0 @
$end

#5000
1!
11

#10000
0!
01

#15000
1!
0"
b101 #
b1101111010100 $
b10111111110110 %
b1 &
b1111010100000000 -
b1 .
11
02
b101 3
b1101111010100 4
b10111111110110 5
b1 6
b101 9
b1101111010100 :
b10111111110110 ;
b1 <
b1111010100000000 =

#20000
0!
01

#25000
1!
11
b1111010100000000 >
b1 ?

#30000
0!
01

#35000
1!
b1111010100000000 )
1*
0+
11

#36000
b0 #
b110001011000001 $
b1111100001000011 %
b101101100000100 -
b0 .
b0 3
b110001011000001 4
b1111100001000011 5
b1 @

#40000
0!
01

#45000
1!
11
b0 9
b110001011000001 :
b1111100001000011 ;
b101101100000100 =

#50000
0!
01

#55000
1!
11
b101101100000100 >

#60000
0!
01

#65000
1!
b101101100000100 )
0*
11

#66000
b111 #
b110101111001101 $
b1010000010111 %
b0 -
b1 /
b111 3
b110101111001101 4
b1010000010111 5
b10 @

#70000
0!
01

#75000
1!
11
b111 9
b110101111001101 :
b1010000010111 ;
b0 =

#80000
0!
01

#85000
1!
11
b0 >

#90000
0!
01

#95000
1!
b0 )
1+
11

#96000
b10 #
b1001110110010010 $
b111011011011000 %
b1010010010000 -
b0 /
b10 3
b1001110110010010 4
b111011011011000 5
b11 @

#100000
0!
01

#105000
1!
11
b10 9
b1001110110010010 :
b111011011011000 ;
b1010010010000 =

#110000
0!
01

#115000
1!
11
b1010010010000 >

#120000
0!
01

#125000
1!
b1010010010000 )
0+
11

#126000
b1 #
b1100100100111010 $
b1110001010100101 %
b1110011010010101 -
b1 .
b1 3
b1100100100111010 4
b1110001010100101 5
b100 @

#130000
0!
01

#135000
1!
11
b1 9
b1100100100111010 :
b1110001010100101 ;
b1110011010010101 =

#140000
0!
01

#145000
1!
11
b1110011010010101 >

#150000
0!
01

#155000
1!
b1110011010010101 )
1*
11

#156000
b10010011011001 $
b1000000000110111 %
b1010010010100010 -
b10010011011001 4
b1000000000110111 5
b101 @

#160000
0!
01

#165000
1!
11
b10010011011001 :
b1000000000110111 ;
b1010010010100010 =

#170000
0!
01

#175000
1!
11
b1010010010100010 >

#180000
0!
01

#185000
1!
b1010010010100010 )
11

#186000
b111 #
b111100010111011 $
b100100101110010 %
b0 -
b0 .
b1 /
b111 3
b111100010111011 4
b100100101110010 5
b110 @

#190000
0!
01

#195000
1!
11
b111 9
b111100010111011 :
b100100101110010 ;
b0 =

#200000
0!
01

#205000
1!
11
b0 >

#210000
0!
01

#215000
1!
b0 )
0*
1+
11

#216000
b110 #
b1110000010110100 $
b110111001001011 %
b11100 -
b0 /
b110 3
b1110000010110100 4
b110111001001011 5
b111 @

#220000
0!
01

#225000
1!
11
b110 9
b1110000010110100 :
b110111001001011 ;
b11100 =

#230000
0!
01

#235000
1!
11
b11100 >

#240000
0!
01

#245000
1!
b11100 )
0+
11

#246000
b0 #
b1011111110000110 $
b1110011100000111 %
b1010011010001101 -
b1 .
b0 3
b1011111110000110 4
b1110011100000111 5
b1000 @

#250000
0!
01

#255000
1!
11
b0 9
b1011111110000110 :
b1110011100000111 ;
b1010011010001101 =

#260000
0!
01

#265000
1!
11
b1010011010001101 >

#270000
0!
01

#275000
1!
b1010011010001101 )
1*
11

#276000
b100 #
b1000000011111101 $
b1100011110111011 %
b100011101000110 -
b0 .
b100 3
b1000000011111101 4
b1100011110111011 5
b1001 @

#280000
0!
01

#285000
1!
11
b100 9
b1000000011111101 :
b1100011110111011 ;
b100011101000110 =

#290000
0!
01

#295000
1!
11
b100011101000110 >

#300000
0!
01

#305000
1!
b100011101000110 )
0*
11

#306000
b11 #
b1100001010101011 $
b1000011101000001 %
b1100011111101011 -
b1 .
b11 3
b1100001010101011 4
b1000011101000001 5
b1010 @

#310000
0!
01

#315000
1!
11
b11 9
b1100001010101011 :
b1000011101000001 ;
b1100011111101011 =

#320000
0!
01

#325000
1!
11
b1100011111101011 >

#330000
0!
01

#335000
1!
b1100011111101011 )
1*
11

#336000
b110 #
b100110111001100 $
b100000111110 %
b1 -
b0 .
b110 3
b100110111001100 4
b100000111110 5
b1011 @

#340000
0!
01

#345000
1!
11
b110 9
b100110111001100 :
b100000111110 ;
b1 =

#350000
0!
01

#355000
1!
11
b1 >

#360000
0!
01

#365000
1!
b1 )
0*
11

#366000
b0 #
b100011100111000 $
b1100101011101010 %
b1001000100010 -
b0 3
b100011100111000 4
b1100101011101010 5
b1100 @

#370000
0!
01

#375000
1!
11
b0 9
b100011100111000 :
b1100101011101010 ;
b1001000100010 =

#380000
0!
01

#385000
1!
11
b1001000100010 >

#390000
0!
01

#395000
1!
b1001000100010 )
11

#396000
b110 #
b10011110101011 $
b1100010110110 %
b10011110 -
b110 3
b10011110101011 4
b1100010110110 5
b1101 @

#400000
0!
01

#405000
1!
11
b110 9
b10011110101011 :
b1100010110110 ;
b10011110 =

#410000
0!
01

#415000
1!
11
b10011110 >

#420000
0!
01

#425000
1!
b10011110 )
11

#426000
b0 #
b1100111111011001 $
b101111111101110 %
b10111111000111 -
b0 3
b1100111111011001 4
b101111111101110 5
b1110 @

#430000
0!
01

#435000
1!
11
b0 9
b1100111111011001 :
b101111111101110 ;
b10111111000111 =

#440000
0!
01

#445000
1!
11
b10111111000111 >

#450000
0!
01

#455000
1!
b10111111000111 )
11

#456000
b110 #
b1111111101001001 $
b1000011110011001 %
b1111111 -
b110 3
b1111111101001001 4
b1000011110011001 5
b1111 @

#460000
0!
01

#465000
1!
11
b110 9
b1111111101001001 :
b1000011110011001 ;
b1111111 =

#470000
0!
01

#475000
1!
11
b1111111 >

#480000
0!
01

#485000
1!
b1111111 )
11

#486000
b100 #
b11011011111000 $
b101011101110010 %
b110000110001010 -
b100 3
b11011011111000 4
b101011101110010 5
b10000 @

#490000
0!
01

#495000
1!
11
b100 9
b11011011111000 :
b101011101110010 ;
b110000110001010 =

#500000
0!
01

#505000
1!
11
b110000110001010 >

#510000
0!
01

#515000
1!
b110000110001010 )
11

#516000
b101 #
b11100110010000 $
b101011010111100 %
b0 -
b1 /
b101 3
b11100110010000 4
b101011010111100 5
b10001 @

#520000
0!
01

#525000
1!
11
b101 9
b11100110010000 :
b101011010111100 ;
b0 =

#530000
0!
01

#535000
1!
11
b0 >

#540000
0!
01

#545000
1!
b0 )
1+
11

#546000
b0 #
b101010011011111 $
b1000110110110100 %
b1110001010010011 -
b1 .
b0 /
b0 3
b101010011011111 4
b1000110110110100 5
b10010 @

#550000
0!
01

#555000
1!
11
b0 9
b101010011011111 :
b1000110110110100 ;
b1110001010010011 =

#560000
0!
01

#565000
1!
11
b1110001010010011 >

#570000
0!
01

#575000
1!
b1110001010010011 )
1*
0+
11

#576000
b100 #
b1101000000011011 $
b1100011101000100 %
b1011101011111 -
b0 .
b100 3
b1101000000011011 4
b1100011101000100 5
b10011 @

#580000
0!
01

#585000
1!
11
b100 9
b1101000000011011 :
b1100011101000100 ;
b1011101011111 =

#590000
0!
01

#595000
1!
11
b1011101011111 >

#600000
0!
01

#605000
1!
b1011101011111 )
0*
11

#606000
b0 #
b1101001011110001 $
b1110000100011 %
b1110111100010100 -
b1 .
b0 3
b1101001011110001 4
b1110000100011 5
b10100 @

#610000
0!
01

#615000
1!
11
b0 9
b1101001011110001 :
b1110000100011 ;
b1110111100010100 =

#620000
0!
01

#625000
1!
11
b1110111100010100 >

#630000
0!
01

#635000
1!
b1110111100010100 )
1*
11

#636000
b100 #
b10110100111001 $
b1110110000111111 %
b1100000100000110 -
b100 3
b10110100111001 4
b1110110000111111 5
b10101 @

#640000
0!
01

#645000
1!
11
b100 9
b10110100111001 :
b1110110000111111 ;
b1100000100000110 =

#650000
0!
01

#655000
1!
11
b1100000100000110 >

#660000
0!
01

#665000
1!
b1100000100000110 )
11

#666000
b0 #
b1101111000111101 $
b1011111100110000 %
b1001110101101101 -
b0 3
b1101111000111101 4
b1011111100110000 5
b10110 @

#670000
0!
01

#675000
1!
11
b0 9
b1101111000111101 :
b1011111100110000 ;
b1001110101101101 =

#680000
0!
01

#685000
1!
11
b1001110101101101 >

#690000
0!
01

#695000
1!
b1001110101101101 )
11

#696000
b111 #
b1110011110101 $
b1110110001101001 %
b0 -
b0 .
b1 /
b111 3
b1110011110101 4
b1110110001101001 5
b10111 @

#700000
0!
01

#705000
1!
11
b111 9
b1110011110101 :
b1110110001101001 ;
b0 =

#710000
0!
01

#715000
1!
11
b0 >

#720000
0!
01

#725000
1!
b0 )
0*
1+
11

#726000
b10001011110001 $
b1100101010100110 %
b10001011110001 4
b1100101010100110 5
b11000 @

#730000
0!
01

#735000
1!
11
b10001011110001 :
b1100101010100110 ;

#740000
0!
01

#745000
1!
11

#750000
0!
01

#755000
1!
11

#756000
b0 #
b100010100010001 $
b1110011110011011 %
b10110010101100 -
b0 /
b0 3
b100010100010001 4
b1110011110011011 5
b11001 @

#760000
0!
01

#765000
1!
11
b0 9
b100010100010001 :
b1110011110011011 ;
b10110010101100 =

#770000
0!
01

#775000
1!
11
b10110010101100 >

#780000
0!
01

#785000
1!
b10110010101100 )
0+
11

#786000
b110 #
b101001101110000 $
b101010001100 %
b101 -
b110 3
b101001101110000 4
b101010001100 5
b11010 @

#790000
0!
01

#795000
1!
11
b110 9
b101001101110000 :
b101010001100 ;
b101 =

#800000
0!
01

#805000
1!
11
b101 >

#810000
0!
01

#815000
1!
b101 )
11

#816000
b1 #
b10000011111111 $
b100111110011110 %
b1101000101100001 -
b1 .
b1 3
b10000011111111 4
b100111110011110 5
b11011 @

#820000
0!
01

#825000
1!
11
b1 9
b10000011111111 :
b100111110011110 ;
b1101000101100001 =

#830000
0!
01

#835000
1!
11
b1101000101100001 >

#840000
0!
01

#845000
1!
b1101000101100001 )
1*
11

#846000
b101 #
b1101101011110111 $
b1010001100001110 %
b1100000000000000 -
b101 3
b1101101011110111 4
b1010001100001110 5
b11100 @

#850000
0!
01

#855000
1!
11
b101 9
b1101101011110111 :
b1010001100001110 ;
b1100000000000000 =

#860000
0!
01

#865000
1!
11
b1100000000000000 >

#870000
0!
01

#875000
1!
b1100000000000000 )
11

#876000
b11 #
b101111110010101 $
b1100010000001110 %
b1101111110011111 -
b11 3
b101111110010101 4
b1100010000001110 5
b11101 @

#880000
0!
01

#885000
1!
11
b11 9
b101111110010101 :
b1100010000001110 ;
b1101111110011111 =

#890000
0!
01

#895000
1!
11
b1101111110011111 >

#900000
0!
01

#905000
1!
b1101111110011111 )
11

#906000
b10 #
b1100101111001110 $
b1001111100000101 %
b1000101100000100 -
b10 3
b1100101111001110 4
b1001111100000101 5
b11110 @

#910000
0!
01

#915000
1!
11
b10 9
b1100101111001110 :
b1001111100000101 ;
b1000101100000100 =

#920000
0!
01

#925000
1!
11
b1000101100000100 >

#930000
0!
01

#935000
1!
b1000101100000100 )
11

#936000
b0 #
b100001010010100 $
b1111111010011011 %
b100000100101111 -
b0 .
b0 3
b100001010010100 4
b1111111010011011 5
b11111 @

#940000
0!
01

#945000
1!
11
b0 9
b100001010010100 :
b1111111010011011 ;
b100000100101111 =

#950000
0!
01

#955000
1!
11
b100000100101111 >

#960000
0!
01

#965000
1!
b100000100101111 )
0*
11

#966000
b101 #
b100011110111 $
b1100101001101001 %
b1110111000000000 -
b1 .
b101 3
b100011110111 4
b1100101001101001 5
b100000 @

#970000
0!
01

#975000
1!
11
b101 9
b100011110111 :
b1100101001101001 ;
b1110111000000000 =

#980000
0!
01

#985000
1!
11
b1110111000000000 >

#990000
0!
01

#995000
1!
b1110111000000000 )
1*
11

#996000
b0 #
b111001001101001 $
b110011111101 %
b111111101100110 -
b0 .
b0 3
b111001001101001 4
b110011111101 5
b100001 @

#1000000
0!
01

#1005000
1!
11
b0 9
b111001001101001 :
b110011111101 ;
b111111101100110 =

#1010000
0!
01

#1015000
1!
11
b111111101100110 >

#1020000
0!
01

#1025000
1!
b111111101100110 )
0*
11

#1026000
b10 #
b1001111111101001 $
b1010111110101 %
b1010111100001 -
b10 3
b1001111111101001 4
b1010111110101 5
b100010 @

#1030000
0!
01

#1035000
1!
11
b10 9
b1001111111101001 :
b1010111110101 ;
b1010111100001 =

#1040000
0!
01

#1045000
1!
11
b1010111100001 >

#1050000
0!
01

#1055000
1!
b1010111100001 )
11

#1056000
b111 #
b110110001101111 $
b1000100001011110 %
b0 -
b1 /
b111 3
b110110001101111 4
b1000100001011110 5
b100011 @

#1060000
0!
01

#1065000
1!
11
b111 9
b110110001101111 :
b1000100001011110 ;
b0 =

#1070000
0!
01

#1075000
1!
11
b0 >

#1080000
0!
01

#1085000
1!
b0 )
1+
11

#1086000
b100 #
b11011110001111 $
b10100001001000 %
b1111111000111 -
b0 /
b100 3
b11011110001111 4
b10100001001000 5
b100100 @

#1090000
0!
01

#1095000
1!
11
b100 9
b11011110001111 :
b10100001001000 ;
b1111111000111 =

#1100000
0!
01

#1105000
1!
11
b1111111000111 >

#1110000
0!
01

#1115000
1!
b1111111000111 )
0+
11

#1116000
b11 #
b1100110100011001 $
b1001010010110111 %
b1101110110111111 -
b1 .
b11 3
b1100110100011001 4
b1001010010110111 5
b100101 @

#1120000
0!
01

#1125000
1!
11
b11 9
b1100110100011001 :
b1001010010110111 ;
b1101110110111111 =

#1130000
0!
01

#1135000
1!
11
b1101110110111111 >

#1140000
0!
01

#1145000
1!
b1101110110111111 )
1*
11

#1146000
b110111110100001 $
b1100110001000110 %
b1110111111100111 -
b110111110100001 4
b1100110001000110 5
b100110 @

#1150000
0!
01

#1155000
1!
11
b110111110100001 :
b1100110001000110 ;
b1110111111100111 =

#1160000
0!
01

#1165000
1!
11
b1110111111100111 >

#1170000
0!
01

#1175000
1!
b1110111111100111 )
11

#1176000
b10 #
b10100000011101 $
b1001100101100000 %
b100000000000 -
b0 .
b10 3
b10100000011101 4
b1001100101100000 5
b100111 @

#1180000
0!
01

#1185000
1!
11
b10 9
b10100000011101 :
b1001100101100000 ;
b100000000000 =

#1190000
0!
01

#1195000
1!
11
b100000000000 >

#1200000
0!
01

#1205000
1!
b100000000000 )
0*
11

#1206000
b0 #
b110100011111000 $
b100100000001 %
b111000111111001 -
b0 3
b110100011111000 4
b100100000001 5
b101000 @

#1210000
0!
01

#1215000
1!
11
b0 9
b110100011111000 :
b100100000001 ;
b111000111111001 =

#1220000
0!
01

#1225000
1!
11
b111000111111001 >

#1230000
0!
01

#1235000
1!
b111000111111001 )
11

#1236000
b1101001000011011 $
b11000100011110 %
b1100111001 -
b1101001000011011 4
b11000100011110 5
b101001 @

#1240000
0!
01

#1245000
1!
11
b1101001000011011 :
b11000100011110 ;
b1100111001 =

#1250000
0!
01

#1255000
1!
11
b1100111001 >

#1260000
0!
01

#1265000
1!
b1100111001 )
11

#1266000
b1 #
b1100111111110101 $
b1001101000010111 %
b11010111011110 -
b1 3
b1100111111110101 4
b1001101000010111 5
b101010 @

#1270000
0!
01

#1275000
1!
11
b1 9
b1100111111110101 :
b1001101000010111 ;
b11010111011110 =

#1280000
0!
01

#1285000
1!
11
b11010111011110 >

#1290000
0!
01

#1295000
1!
b11010111011110 )
11

#1296000
b0 #
b1001101000010110 $
b110110000110010 %
b11001001000 -
b0 3
b1001101000010110 4
b110110000110010 5
b101011 @

#1300000
0!
01

#1305000
1!
11
b0 9
b1001101000010110 :
b110110000110010 ;
b11001001000 =

#1310000
0!
01

#1315000
1!
11
b11001001000 >

#1320000
0!
01

#1325000
1!
b11001001000 )
11

#1326000
b111 #
b1111110110010110 $
b11110000101000 %
b0 -
b1 /
b111 3
b1111110110010110 4
b11110000101000 5
b101100 @

#1330000
0!
01

#1335000
1!
11
b111 9
b1111110110010110 :
b11110000101000 ;
b0 =

#1340000
0!
01

#1345000
1!
11
b0 >

#1350000
0!
01

#1355000
1!
b0 )
1+
11

#1356000
b1 #
b110101000011000 $
b1101011000111110 %
b1001001111011010 -
b1 .
b0 /
b1 3
b110101000011000 4
b1101011000111110 5
b101101 @

#1360000
0!
01

#1365000
1!
11
b1 9
b110101000011000 :
b1101011000111110 ;
b1001001111011010 =

#1370000
0!
01

#1375000
1!
11
b1001001111011010 >

#1380000
0!
01

#1385000
1!
b1001001111011010 )
1*
0+
11

#1386000
b11110111000 $
b1101001111010100 %
b11001111100100 -
b0 .
b11110111000 4
b1101001111010100 5
b101110 @

#1390000
0!
01

#1395000
1!
11
b11110111000 :
b1101001111010100 ;
b11001111100100 =

#1400000
0!
01

#1405000
1!
11
b11001111100100 >

#1410000
0!
01

#1415000
1!
b11001111100100 )
0*
11

#1416000
b111 #
b11111101101111 $
b11110111101100 %
b0 -
b1 /
b111 3
b11111101101111 4
b11110111101100 5
b101111 @

#1420000
0!
01

#1425000
1!
11
b111 9
b11111101101111 :
b11110111101100 ;
b0 =

#1430000
0!
01

#1435000
1!
11
b0 >

#1440000
0!
01

#1445000
1!
b0 )
1+
11

#1446000
b100 #
b1110001101011000 $
b100010110100100 %
b1010011011111100 -
b1 .
b0 /
b100 3
b1110001101011000 4
b100010110100100 5
b110000 @

#1450000
0!
01

#1455000
1!
11
b100 9
b1110001101011000 :
b100010110100100 ;
b1010011011111100 =

#1460000
0!
01

#1465000
1!
11
b1010011011111100 >

#1470000
0!
01

#1475000
1!
b1010011011111100 )
1*
0+
11

#1476000
b0 #
b1100001101101010 $
b1000010100010011 %
b100100001111101 -
b0 .
b0 3
b1100001101101010 4
b1000010100010011 5
b110001 @

#1480000
0!
01

#1485000
1!
11
b0 9
b1100001101101010 :
b1000010100010011 ;
b100100001111101 =

#1490000
0!
01

#1495000
1!
11
b100100001111101 >

#1500000
0!
01

#1505000
1!
b100100001111101 )
0*
11

#1506000
b101 #
b111100110111001 $
b110100001101100 %
b1001000000000000 -
b1 .
b101 3
b111100110111001 4
b110100001101100 5
b110010 @

#1510000
0!
01

#1515000
1!
11
b101 9
b111100110111001 :
b110100001101100 ;
b1001000000000000 =

#1520000
0!
01

#1525000
1!
11
b1001000000000000 >

#1530000
0!
01

#1535000
1!
b1001000000000000 )
1*
11

#1536000
b0 #
b1111011101 $
b10101111010110 %
b10111110110011 -
b0 .
b0 3
b1111011101 4
b10101111010110 5
b110011 @

#1540000
0!
01

#1545000
1!
11
b0 9
b1111011101 :
b10101111010110 ;
b10111110110011 =

#1550000
0!
01

#1555000
1!
11
b10111110110011 >

#1560000
0!
01

#1565000
1!
b10111110110011 )
0*
11

#1566000
b100 #
b1100101111101110 $
b1010010110001111 %
b110111001100001 -
b100 3
b1100101111101110 4
b1010010110001111 5
b110100 @

#1570000
0!
01

#1575000
1!
11
b100 9
b1100101111101110 :
b1010010110001111 ;
b110111001100001 =

#1580000
0!
01

#1585000
1!
11
b110111001100001 >

#1590000
0!
01

#1595000
1!
b110111001100001 )
11

#1596000
b10 #
b1101100110100011 $
b1010100101101101 %
b1000100100100001 -
b1 .
b10 3
b1101100110100011 4
b1010100101101101 5
b110101 @

#1600000
0!
01

#1605000
1!
11
b10 9
b1101100110100011 :
b1010100101101101 ;
b1000100100100001 =

#1610000
0!
01

#1615000
1!
11
b1000100100100001 >

#1620000
0!
01

#1625000
1!
b1000100100100001 )
1*
11

#1626000
b110110001101011 $
b111010101011011 %
b110010001001011 -
b0 .
b110110001101011 4
b111010101011011 5
b110110 @

#1630000
0!
01

#1635000
1!
11
b110110001101011 :
b111010101011011 ;
b110010001001011 =

#1640000
0!
01

#1645000
1!
11
b110010001001011 >

#1650000
0!
01

#1655000
1!
b110010001001011 )
0*
11

#1656000
b111 #
b110011110100000 $
b100111011111110 %
b0 -
b1 /
b111 3
b110011110100000 4
b100111011111110 5
b110111 @

#1660000
0!
01

#1665000
1!
11
b111 9
b110011110100000 :
b100111011111110 ;
b0 =

#1670000
0!
01

#1675000
1!
11
b0 >

#1680000
0!
01

#1685000
1!
b0 )
1+
11

#1686000
b10 #
b1000111010101010 $
b1011101101101001 %
b1000101000101000 -
b1 .
b0 /
b10 3
b1000111010101010 4
b1011101101101001 5
b111000 @

#1690000
0!
01

#1695000
1!
11
b10 9
b1000111010101010 :
b1011101101101001 ;
b1000101000101000 =

#1700000
0!
01

#1705000
1!
11
b1000101000101000 >

#1710000
0!
01

#1715000
1!
b1000101000101000 )
1*
0+
11

#1716000
b0 #
b101101101000100 $
b10001100001001 %
b111111001001101 -
b0 .
b0 3
b101101101000100 4
b10001100001001 5
b111001 @

#1720000
0!
01

#1725000
1!
11
b0 9
b101101101000100 :
b10001100001001 ;
b111111001001101 =

#1730000
0!
01

#1735000
1!
11
b111111001001101 >

#1740000
0!
01

#1745000
1!
b111111001001101 )
0*
11

#1746000
b1 #
b1101000101001011 $
b1011000110110100 %
b1111110010111 -
b1 3
b1101000101001011 4
b1011000110110100 5
b111010 @

#1750000
0!
01

#1755000
1!
11
b1 9
b1101000101001011 :
b1011000110110100 ;
b1111110010111 =

#1760000
0!
01

#1765000
1!
11
b1111110010111 >

#1770000
0!
01

#1775000
1!
b1111110010111 )
11

#1776000
b11 #
b1011110010101101 $
b110011111000 %
b1011110011111101 -
b1 .
b11 3
b1011110010101101 4
b110011111000 5
b111011 @

#1780000
0!
01

#1785000
1!
11
b11 9
b1011110010101101 :
b110011111000 ;
b1011110011111101 =

#1790000
0!
01

#1795000
1!
11
b1011110011111101 >

#1800000
0!
01

#1805000
1!
b1011110011111101 )
1*
11

#1806000
b111 #
b1111011100001101 $
b1101111001000100 %
b0 -
b0 .
b1 /
b111 3
b1111011100001101 4
b1101111001000100 5
b111100 @

#1810000
0!
01

#1815000
1!
11
b111 9
b1111011100001101 :
b1101111001000100 ;
b0 =

#1820000
0!
01

#1825000
1!
11
b0 >

#1830000
0!
01

#1835000
1!
b0 )
0*
1+
11

#1836000
b1110110011010111 $
b1001101011110001 %
b1110110011010111 4
b1001101011110001 5
b111101 @

#1840000
0!
01

#1845000
1!
11
b1110110011010111 :
b1001101011110001 ;

#1850000
0!
01

#1855000
1!
11

#1860000
0!
01

#1865000
1!
11

#1866000
b11 #
b10110101010 $
b1001000111111111 %
b1001010111111111 -
b1 .
b0 /
b11 3
b10110101010 4
b1001000111111111 5
b111110 @

#1870000
0!
01

#1875000
1!
11
b11 9
b10110101010 :
b1001000111111111 ;
b1001010111111111 =

#1880000
0!
01

#1885000
1!
11
b1001010111111111 >

#1890000
0!
01

#1895000
1!
b1001010111111111 )
1*
0+
11

